{
  "discord_user": {
    "id": "1379709311873187910",
    "username": "81yb",
    "avatar": "https://cdn.discordapp.com/avatars/1379709311873187910/ec6760a1efcd8a786a7394d97094d04c.png",
    "discord_status": "online",
    "activities": [
      {
        "id": "custom",
        "name": "Custom Status",
        "type": 4,
        "state": ".gg/gun",
        "timestamps": {},
        "created_at": 1751094864069
      },
      {
        "name": "Spotify",
        "type": 2,
        "state": "J. Cole",
        "timestamps": {
          "start": "2025-06-28T07:32:23.899Z",
          "end": "2025-06-28T07:36:19.219Z"
        },
        "created_at": 1751095944652
      }
    ],
    "global_name": "᲼",
    "display_name": "᲼"
  }
}