{
  "discord_user": {
    "id": "1379709311873187910",
    "username": "81yb",
    "avatar": "https://cdn.discordapp.com/avatars/1379709311873187910/ec6760a1efcd8a786a7394d97094d04c.png",
    "discord_status": "online",
    "activities": [
      {
        "id": "custom",
        "name": "Custom Status",
        "type": 4,
        "state": ".gg/gun",
        "timestamps": {},
        "created_at": 1751164928703
      },
      {
        "name": "Spotify",
        "type": 2,
        "state": "B Jack$; ZEDDY WILL",
        "timestamps": {
          "start": "2025-06-29T03:30:43.819Z",
          "end": "2025-06-29T03:32:41.972Z"
        },
        "created_at": 1751167845193
      },
      {
        "name": "MiGhettoRZ",
        "type": 0,
        "state": "[103/200] Players",
        "timestamps": {
          "start": "2025-06-29T02:44:35.000Z",
          "end": null
        },
        "created_at": 1751167832361
      },
      {
        "name": "Grand Theft Auto V",
        "type": 0,
        "state": null,
        "timestamps": {
          "start": "2025-06-29T02:44:07.641Z",
          "end": null
        },
        "created_at": 1751165048631
      }
    ],
    "global_name": "᲼",
    "display_name": "᲼"
  }
}