{
  "discord_user": {
    "id": "872658221821726811",
    "username": "me.ech",
    "avatar": "https://cdn.discordapp.com/avatars/872658221821726811/29778ca7b4e41f1dad0566ff301af91d.png",
    "discord_status": "online",
    "activities": [
      {
        "id": "custom",
        "name": "Custom Status",
        "type": 4,
        "state": "ain't it fun.",
        "timestamps": {},
        "created_at": 1752812316089
      },
      {
        "name": "Spotify",
        "type": 2,
        "state": "Lil Tecca",
        "timestamps": {
          "start": "2025-07-18T06:22:01.644Z",
          "end": "2025-07-18T06:24:14.567Z"
        },
        "created_at": 1752819732198
      }
    ],
    "global_name": "m",
    "display_name": "m"
  }
}